llama_index/llms/gigachat/__init__.py
llama_index/llms/gigachat/base.py
llama_index_llms_gigachat_ru-0.4.1.dist-info/METADATA
llama_index_llms_gigachat_ru-0.4.1.dist-info/WHEEL
llama_index_llms_gigachat_ru-0.4.1.dist-info/licenses/LICENSE
llama_index_llms_gigachat_ru-0.4.1.dist-info/RECORD
