Metadata-Version: 2.4
Name: llama-index-llms-gigachat-ru
Version: 0.4.1
Summary: llama-index llms gigachat integration
Author-email: Pavlin Nikolay <afaneor@gmail.com>
License-Expression: MIT
License-File: LICENSE
Requires-Python: <4.0,>=3.9
Requires-Dist: gigachat<0.2,>=0.1.33
Requires-Dist: llama-index-core<0.15,>=0.13.0
